CHANGELOG.md
LICENSE
README.md
sqlitekg2vec/__init__.py
sqlitekg2vec/io.py
sqlitekg2vec/kg.py
sqlitekg2vec-0.2.0.dist-info/LICENSE
sqlitekg2vec-0.2.0.dist-info/WHEEL
sqlitekg2vec-0.2.0.dist-info/METADATA
sqlitekg2vec-0.2.0.dist-info/RECORD
