Metadata-Version: 2.1
Name: sqlitekg2vec
Version: 0.2.0
Summary: SQLiteKG implements the KG class from pyRDF2Vec by using a local SQLite database for storing and querying a KG.
Home-page: https://github.com/khaller93/sqlitekg2vec
Keywords: embeddings,knowledge-graph,rdf2vec,word2vec,sqlite
Author: Kevin Haller
Author-email: contact@kevinhaller.dev
Requires-Python: >=3.8,<4.0
Classifier: Programming Language :: Python :: 3
Classifier: Programming Language :: Python :: 3.8
Classifier: Programming Language :: Python :: 3.9
Classifier: Programming Language :: Python :: 3.10
Classifier: Programming Language :: Python :: 3.11
Requires-Dist: aiohttp (>=3.8.1,<4.0.0)
Requires-Dist: gensim (>=4.0.1,<5.0.0)
Requires-Dist: nest_asyncio (>=1.5.4,<2.0.0)
Requires-Dist: pyrdf2vec (>=0.2.3)
Requires-Dist: rdflib (>=6.1.1,<7.0.0)
Project-URL: Repository, https://github.com/khaller93/sqlitekg2vec
